mpw/__init__.py
mpw/algorithm.py
mpw/cli.py
mpw/commands.py
mpw/config.py
mpw/exchange.py
mpw/algorithm/__init__.py
mpw/algorithm/v1.py
mpw/algorithm/v2.py
mpw/algorithm/v3.py
mpw-0.4.dist-info/DESCRIPTION.rst
mpw-0.4.dist-info/entry_points.txt
mpw-0.4.dist-info/METADATA
mpw-0.4.dist-info/metadata.json
mpw-0.4.dist-info/RECORD
mpw-0.4.dist-info/top_level.txt
mpw-0.4.dist-info/WHEEL
