Metadata-Version: 2.0
Name: mpw
Version: 0.4
Summary: A Python implementation of the Master Password algorithm.
Home-page: https://bitbucket.org/ssc/mpw
Author: Stefan Scherfke
Author-email: stefan at sofa-rockers.org
License: MIT License
Platform: UNKNOWN
Classifier: Development Status :: 3 - Alpha
Classifier: Environment :: Console
Classifier: Intended Audience :: Developers
Classifier: Intended Audience :: End Users/Desktop
Classifier: License :: OSI Approved :: MIT License
Classifier: Natural Language :: English
Classifier: Operating System :: OS Independent
Classifier: Programming Language :: Python
Classifier: Programming Language :: Python :: 3
Classifier: Programming Language :: Python :: 3.4
Classifier: Topic :: Security
Requires-Dist: click (>=3.3)
Requires-Dist: cryptography (>=0.7.2)
Requires-Dist: pyperclip (>=1.5.7)
Requires-Dist: scrypt (>=0.6.1)
